smdamenprofiling/__init__.py
smdamenprofiling/dataprofile.py
smdamenprofiling-0.1.14.dist-info/METADATA
smdamenprofiling-0.1.14.dist-info/WHEEL
smdamenprofiling-0.1.14.dist-info/top_level.txt
smdamenprofiling-0.1.14.dist-info/RECORD
