Metadata-Version: 2.4
Name: smdamenprofiling
Version: 0.1.14
Summary: Damen-library
Author-email: giandaeky <giandaekyoga10@gmail.com>
License: MIT
Project-URL: Homepage, https://pypi.org/project/damen-profiling/
Requires-Python: >=3.8
